stimula/__init__.py
stimula/__pycache__/__init__.cpython-312.pyc
stimula/cli/__init__.py
stimula/cli/anonymizer.py
stimula/cli/cli.py
stimula/cli/file_source.py
stimula/cli/google_source.py
stimula/cli/local.py
stimula/cli/remote.py
stimula/cli/__pycache__/__init__.cpython-312.pyc
stimula/cli/__pycache__/anonymizer.cpython-312.pyc
stimula/cli/__pycache__/cli.cpython-312.pyc
stimula/cli/__pycache__/file_source.cpython-312.pyc
stimula/cli/__pycache__/google_source.cpython-312.pyc
stimula/cli/__pycache__/local.cpython-312.pyc
stimula/cli/__pycache__/remote.cpython-312.pyc
stimula/service/__init__.py
stimula/service/abstract_orm.py
stimula/service/api_reader.py
stimula/service/auth.py
stimula/service/context.py
stimula/service/csv_reader.py
stimula/service/db.py
stimula/service/db_reader.py
stimula/service/diff_to_executor.py
stimula/service/executor_creator.py
stimula/service/executor_service.py
stimula/service/model_service.py
stimula/service/orm_creator.py
stimula/service/orm_executor.py
stimula/service/query_executor.py
stimula/service/reporter.py
stimula/service/sql_creator.py
stimula/service/__pycache__/__init__.cpython-312.pyc
stimula/service/__pycache__/abstract_orm.cpython-312.pyc
stimula/service/__pycache__/api_reader.cpython-312.pyc
stimula/service/__pycache__/auth.cpython-312.pyc
stimula/service/__pycache__/context.cpython-312.pyc
stimula/service/__pycache__/csv_reader.cpython-312.pyc
stimula/service/__pycache__/db.cpython-312.pyc
stimula/service/__pycache__/db_reader.cpython-312.pyc
stimula/service/__pycache__/diff_to_executor.cpython-312.pyc
stimula/service/__pycache__/executor_creator.cpython-312.pyc
stimula/service/__pycache__/executor_service.cpython-312.pyc
stimula/service/__pycache__/model_service.cpython-312.pyc
stimula/service/__pycache__/orm_creator.cpython-312.pyc
stimula/service/__pycache__/orm_executor.cpython-312.pyc
stimula/service/__pycache__/query_executor.cpython-312.pyc
stimula/service/__pycache__/reporter.cpython-312.pyc
stimula-1.3.9.dist-info/LICENSE
stimula-1.3.9.dist-info/METADATA
stimula-1.3.9.dist-info/WHEEL
stimula-1.3.9.dist-info/entry_points.txt
stimula-1.3.9.dist-info/top_level.txt
stimula-1.3.9.dist-info/RECORD
